{
  "generated_at": "2026-05-10T10:16:20.495184",
  "total_simulations": 3,
  "success_count": 3,
  "failed_count": 0,
  "total_duration": 68.87767219543457,
  "simulations": [
    {
      "index": 0,
      "name": "Simulation_001",
      "description": "",
      "status": "success",
      "duration": 24.615039110183716,
      "parameters": {
        "model_dim": 2,
        "nx": 40,
        "ny": 25,
        "Lx": 100.0,
        "Ly": 50.0,
        "t_total": 40.0,
        "dt": 0.1,
        "output_freq": 20,
        "C0": 1.0,
        "C_left": 0.0,
        "C_right": 0.0,
        "C_top": 0.0,
        "C_bottom": 0.0,
        "source_strength": 10.0,
        "source_x": 10.0,
        "source_y": 25.0,
        "source_width": 5.0,
        "D": 1.0,
        "vx": 0.5,
        "vy": 0.0,
        "porosity": 0.3,
        "retardation": 1.0,
        "decay": 0.0,
        "is_heterogeneous": false
      },
      "output_dir": "demo_batch_json\\simulation_001_Simulation_001",
      "metrics": {
        "final_max": 0.189328811519884,
        "final_min": 0.0,
        "final_mean": 0.040687224861848455,
        "final_mass": 217.3462866551734,
        "retention_ratio": 0.6781204143641409
      }
    },
    {
      "index": 1,
      "name": "Simulation_002",
      "description": "",
      "status": "success",
      "duration": 17.86548352241516,
      "parameters": {
        "model_dim": 2,
        "nx": 40,
        "ny": 25,
        "Lx": 100.0,
        "Ly": 50.0,
        "t_total": 40.0,
        "dt": 0.1,
        "output_freq": 20,
        "C0": 1.0,
        "C_left": 0.0,
        "C_right": 0.0,
        "C_top": 0.0,
        "C_bottom": 0.0,
        "source_strength": 10.0,
        "source_x": 10.0,
        "source_y": 25.0,
        "source_width": 5.0,
        "D": 5.0,
        "vx": 0.5,
        "vy": 0.0,
        "porosity": 0.3,
        "retardation": 1.0,
        "decay": 0.0,
        "is_heterogeneous": false
      },
      "output_dir": "demo_batch_json\\simulation_002_Simulation_002",
      "metrics": {
        "final_max": 20.0,
        "final_min": 0.0,
        "final_mean": 8.51361810486855,
        "final_mass": 45478.72919267388,
        "retention_ratio": 141.8936350811425
      }
    },
    {
      "index": 2,
      "name": "Simulation_003",
      "description": "",
      "status": "success",
      "duration": 26.388884782791138,
      "parameters": {
        "model_dim": 2,
        "nx": 40,
        "ny": 25,
        "Lx": 100.0,
        "Ly": 50.0,
        "t_total": 40.0,
        "dt": 0.05,
        "output_freq": 40,
        "C0": 1.0,
        "C_left": 0.0,
        "C_right": 0.0,
        "C_top": 0.0,
        "C_bottom": 0.0,
        "source_strength": 10.0,
        "source_x": 10.0,
        "source_y": 25.0,
        "source_width": 5.0,
        "D": 1.0,
        "vx": 2.0,
        "vy": 0.0,
        "porosity": 0.3,
        "retardation": 1.0,
        "decay": 0.0,
        "is_heterogeneous": false
      },
      "output_dir": "demo_batch_json\\simulation_003_Simulation_003",
      "metrics": {
        "final_max": 8.202256775417869e-08,
        "final_min": 0.0,
        "final_mean": 6.204750608341887e-09,
        "final_mass": 3.314503530097163e-05,
        "retention_ratio": 1.0341251013903147e-07
      }
    }
  ]
}